odoo/addons/account_e-invoice_generate/README.rst
odoo/addons/account_e-invoice_generate/__init__.py
odoo/addons/account_e-invoice_generate/__manifest__.py
odoo/addons/account_e-invoice_generate/i18n/account_e-invoice_generate.pot
odoo/addons/account_e-invoice_generate/i18n/nl_NL.po
odoo/addons/account_e-invoice_generate/models/__init__.py
odoo/addons/account_e-invoice_generate/models/account_invoice.py
odoo/addons/account_e-invoice_generate/models/res_company.py
odoo/addons/account_e-invoice_generate/models/res_config_settings.py
odoo/addons/account_e-invoice_generate/readme/CONFIGURE.rst
odoo/addons/account_e-invoice_generate/readme/CONTRIBUTORS.rst
odoo/addons/account_e-invoice_generate/readme/DESCRIPTION.rst
odoo/addons/account_e-invoice_generate/static/description/icon.png
odoo/addons/account_e-invoice_generate/static/description/index.html
odoo/addons/account_e-invoice_generate/views/res_config_settings.xml
odoo11_addon_account_e_invoice_generate-11.0.1.0.0.99.dev11.dist-info/METADATA
odoo11_addon_account_e_invoice_generate-11.0.1.0.0.99.dev11.dist-info/WHEEL
odoo11_addon_account_e_invoice_generate-11.0.1.0.0.99.dev11.dist-info/top_level.txt
odoo11_addon_account_e_invoice_generate-11.0.1.0.0.99.dev11.dist-info/RECORD
